[
  {
    "head": "华利公司8·16特别重大烟花爆竹爆炸事故",
    "relation": "造成",
    "tail": "34人死亡",
    "source": "事故调查报告_国务院安委会办公室关于黑龙江省伊春市华利实业有限公司“8·16”特别重大烟花爆竹爆炸事故调查处理结果的通报（已失效）.txt"
  },
  {
    "head": "华利公司8·16特别重大烟花爆竹爆炸事故",
    "relation": "造成",
    "tail": "3人失踪",
    "source": "事故调查报告_国务院安委会办公室关于黑龙江省伊春市华利实业有限公司“8·16”特别重大烟花爆竹爆炸事故调查处理结果的通报（已失效）.txt"
  },
  {
    "head": "华利公司8·16特别重大烟花爆竹爆炸事故",
    "relation": "造成",
    "tail": "152人受伤",
    "source": "事故调查报告_国务院安委会办公室关于黑龙江省伊春市华利实业有限公司“8·16”特别重大烟花爆竹爆炸事故调查处理结果的通报（已失效）.txt"
  },
  {
    "head": "华利公司8·16特别重大烟花爆竹爆炸事故",
    "relation": "造成",
    "tail": "直接经济损失6818.40万元",
    "source": "事故调查报告_国务院安委会办公室关于黑龙江省伊春市华利实业有限公司“8·16”特别重大烟花爆竹爆炸事故调查处理结果的通报（已失效）.txt"
  },
  {
    "head": "礼花弹合球工",
    "relation": "操作不慎引发",
    "tail": "爆炸",
    "source": "事故调查报告_国务院安委会办公室关于黑龙江省伊春市华利实业有限公司“8·16”特别重大烟花爆竹爆炸事故调查处理结果的通报（已失效）.txt"
  },
  {
    "head": "华利公司",
    "relation": "存在",
    "tail": "超许可范围生产礼花弹",
    "source": "事故调查报告_国务院安委会办公室关于黑龙江省伊春市华利实业有限公司“8·16”特别重大烟花爆竹爆炸事故调查处理结果的通报（已失效）.txt"
  },
  {
    "head": "华利公司",
    "relation": "存在",
    "tail": "超人员和超药量生产",
    "source": "事故调查报告_国务院安委会办公室关于黑龙江省伊春市华利实业有限公司“8·16”特别重大烟花爆竹爆炸事故调查处理结果的通报（已失效）.txt"
  },
  {
    "head": "华利公司",
    "relation": "存在",
    "tail": "擅自扩大生产区域",
    "source": "事故调查报告_国务院安委会办公室关于黑龙江省伊春市华利实业有限公司“8·16”特别重大烟花爆竹爆炸事故调查处理结果的通报（已失效）.txt"
  },
  {
    "head": "华利公司",
    "relation": "存在",
    "tail": "随意改变工房设计用途",
    "source": "事故调查报告_国务院安委会办公室关于黑龙江省伊春市华利实业有限公司“8·16”特别重大烟花爆竹爆炸事故调查处理结果的通报（已失效）.txt"
  },
  {
    "head": "伊春市安全监管局",
    "relation": "未认真履行",
    "tail": "安全监管职责",
    "source": "事故调查报告_国务院安委会办公室关于黑龙江省伊春市华利实业有限公司“8·16”特别重大烟花爆竹爆炸事故调查处理结果的通报（已失效）.txt"
  },
  {
    "head": "黑龙江省安全监管局",
    "relation": "暂扣",
    "tail": "华利公司安全生产许可证",
    "source": "事故调查报告_国务院安委会办公室关于黑龙江省伊春市华利实业有限公司“8·16”特别重大烟花爆竹爆炸事故调查处理结果的通报（已失效）.txt"
  },
  {
    "head": "国务院安委会办公室",
    "relation": "通报",
    "tail": "事故调查处理结果",
    "source": "事故调查报告_国务院安委会办公室关于黑龙江省伊春市华利实业有限公司“8·16”特别重大烟花爆竹爆炸事故调查处理结果的通报（已失效）.txt"
  },
  {
    "head": "华利公司",
    "relation": "被吊销",
    "tail": "证照",
    "source": "事故调查报告_国务院安委会办公室关于黑龙江省伊春市华利实业有限公司“8·16”特别重大烟花爆竹爆炸事故调查处理结果的通报（已失效）.txt"
  },
  {
    "head": "华利公司",
    "relation": "被罚款",
    "tail": "500万元",
    "source": "事故调查报告_国务院安委会办公室关于黑龙江省伊春市华利实业有限公司“8·16”特别重大烟花爆竹爆炸事故调查处理结果的通报（已失效）.txt"
  },
  {
    "head": "金朝相",
    "relation": "被追究刑事责任",
    "tail": "刑事责任",
    "source": "事故调查报告_国务院安委会办公室关于黑龙江省伊春市华利实业有限公司“8·16”特别重大烟花爆竹爆炸事故调查处理结果的通报（已失效）.txt"
  },
  {
    "head": "人民政府",
    "relation": "需落实",
    "tail": "烟花爆竹安全生产工作",
    "source": "事故调查报告_国务院安委会办公室关于黑龙江省伊春市华利实业有限公司“8·16”特别重大烟花爆竹爆炸事故调查处理结果的通报（已失效）.txt"
  },
  {
    "head": "安全监管局",
    "relation": "应严格审查",
    "tail": "烟花爆竹企业安全条件",
    "source": "事故调查报告_国务院安委会办公室关于黑龙江省伊春市华利实业有限公司“8·16”特别重大烟花爆竹爆炸事故调查处理结果的通报（已失效）.txt"
  },
  {
    "head": "烟花爆竹企业",
    "relation": "必须执行",
    "tail": "《烟花爆竹安全管理条例》",
    "source": "事故调查报告_国务院安委会办公室关于黑龙江省伊春市华利实业有限公司“8·16”特别重大烟花爆竹爆炸事故调查处理结果的通报（已失效）.txt"
  },
  {
    "head": "烟花爆竹企业",
    "relation": "必须杜绝",
    "tail": "三违行为",
    "source": "事故调查报告_国务院安委会办公室关于黑龙江省伊春市华利实业有限公司“8·16”特别重大烟花爆竹爆炸事故调查处理结果的通报（已失效）.txt"
  },
  {
    "head": "烟花爆竹企业",
    "relation": "必须杜绝",
    "tail": "三超一改现象",
    "source": "事故调查报告_国务院安委会办公室关于黑龙江省伊春市华利实业有限公司“8·16”特别重大烟花爆竹爆炸事故调查处理结果的通报（已失效）.txt"
  },
  {
    "head": "有关部门",
    "relation": "应运用",
    "tail": "视频监控系统",
    "source": "事故调查报告_国务院安委会办公室关于黑龙江省伊春市华利实业有限公司“8·16”特别重大烟花爆竹爆炸事故调查处理结果的通报（已失效）.txt"
  },
  {
    "head": "视频监控系统",
    "relation": "用于",
    "tail": "监测违规违章行为",
    "source": "事故调查报告_国务院安委会办公室关于黑龙江省伊春市华利实业有限公司“8·16”特别重大烟花爆竹爆炸事故调查处理结果的通报（已失效）.txt"
  },
  {
    "head": "安全评价机构",
    "relation": "必须承担",
    "tail": "法律责任",
    "source": "事故调查报告_国务院安委会办公室关于黑龙江省伊春市华利实业有限公司“8·16”特别重大烟花爆竹爆炸事故调查处理结果的通报（已失效）.txt"
  }
]