[
  {
    "head": "海上风电的建设方",
    "relation": "需要备案",
    "tail": "应急预案",
    "source": "企业预案_企业应急预案备案咨询.txt"
  },
  {
    "head": "《生产安全事故应急预案管理办法》",
    "relation": "规定",
    "tail": "备案部门由省级负有安全生产监督管理职责的部门确定",
    "source": "企业预案_企业应急预案备案咨询.txt"
  },
  {
    "head": "省、自治区、直辖市人民政府负有安全生产监督管理职责的部门",
    "relation": "确定",
    "tail": "其他生产经营单位应急预案的备案",
    "source": "企业预案_企业应急预案备案咨询.txt"
  },
  {
    "head": "海上风电的建设方",
    "relation": "结合",
    "tail": "企业实际",
    "source": "企业预案_企业应急预案备案咨询.txt"
  },
  {
    "head": "海上风电的建设方",
    "relation": "依据",
    "tail": "地方有关规定",
    "source": "企业预案_企业应急预案备案咨询.txt"
  },
  {
    "head": "海上风电的建设方",
    "relation": "执行",
    "tail": "生产安全事故应急预案备案",
    "source": "企业预案_企业应急预案备案咨询.txt"
  },
  {
    "head": "国家安全生产应急救援中心",
    "relation": "回复",
    "tail": "应急预案备案咨询",
    "source": "企业预案_企业应急预案备案咨询.txt"
  }
]