[
  {
    "head": "生产经营单位",
    "relation": "应当制定",
    "tail": "生产安全事故应急救援预案",
    "source": "企业预案_应急预案备案需要什么材料和办理流程.txt"
  },
  {
    "head": "《安全生产法》第八十一条",
    "relation": "要求",
    "tail": "生产经营单位制定应急预案",
    "source": "企业预案_应急预案备案需要什么材料和办理流程.txt"
  },
  {
    "head": "《生产安全事故应急预案管理办法》",
    "relation": "规定",
    "tail": "应急预案编制、评审、公布、备案、实施",
    "source": "企业预案_应急预案备案需要什么材料和办理流程.txt"
  },
  {
    "head": "应急预案编制",
    "relation": "参考",
    "tail": "《GB/T 29639-2020》",
    "source": "企业预案_应急预案备案需要什么材料和办理流程.txt"
  },
  {
    "head": "《GB/T 29639-2020》",
    "relation": "是",
    "tail": "《生产经营单位生产安全事故应急预案编制导则》",
    "source": "企业预案_应急预案备案需要什么材料和办理流程.txt"
  },
  {
    "head": "国家安全生产应急救援中心",
    "relation": "负责回复",
    "tail": "应急预案备案咨询",
    "source": "企业预案_应急预案备案需要什么材料和办理流程.txt"
  }
]