[
  {
    "head": "EPC总承办项目",
    "relation": "涉及",
    "tail": "应急预案备案问题",
    "source": "企业预案_想咨询EPC总承办项目的应急预案备案问题，是建设单位还是总承办单位？.txt"
  },
  {
    "head": "子公司",
    "relation": "投资",
    "tail": "风电建设项目",
    "source": "企业预案_想咨询EPC总承办项目的应急预案备案问题，是建设单位还是总承办单位？.txt"
  },
  {
    "head": "风电建设项目",
    "relation": "实行",
    "tail": "EPC总承包",
    "source": "企业预案_想咨询EPC总承办项目的应急预案备案问题，是建设单位还是总承办单位？.txt"
  },
  {
    "head": "《生产安全事故应急预案管理办法》",
    "relation": "规定",
    "tail": "生产经营单位应编制应急预案",
    "source": "企业预案_想咨询EPC总承办项目的应急预案备案问题，是建设单位还是总承办单位？.txt"
  },
  {
    "head": "生产经营单位",
    "relation": "根据",
    "tail": "相关法律法规",
    "source": "企业预案_想咨询EPC总承办项目的应急预案备案问题，是建设单位还是总承办单位？.txt"
  },
  {
    "head": "生产经营单位",
    "relation": "结合",
    "tail": "组织管理体系",
    "source": "企业预案_想咨询EPC总承办项目的应急预案备案问题，是建设单位还是总承办单位？.txt"
  },
  {
    "head": "生产经营单位",
    "relation": "结合",
    "tail": "生产规模",
    "source": "企业预案_想咨询EPC总承办项目的应急预案备案问题，是建设单位还是总承办单位？.txt"
  },
  {
    "head": "生产经营单位",
    "relation": "结合",
    "tail": "事故特点",
    "source": "企业预案_想咨询EPC总承办项目的应急预案备案问题，是建设单位还是总承办单位？.txt"
  },
  {
    "head": "生产经营单位",
    "relation": "编制",
    "tail": "应急预案",
    "source": "企业预案_想咨询EPC总承办项目的应急预案备案问题，是建设单位还是总承办单位？.txt"
  },
  {
    "head": "应急预案",
    "relation": "需要与",
    "tail": "相关预案衔接",
    "source": "企业预案_想咨询EPC总承办项目的应急预案备案问题，是建设单位还是总承办单位？.txt"
  },
  {
    "head": "建设单位",
    "relation": "属于",
    "tail": "生产经营单位",
    "source": "企业预案_想咨询EPC总承办项目的应急预案备案问题，是建设单位还是总承办单位？.txt"
  },
  {
    "head": "施工单位",
    "relation": "属于",
    "tail": "生产经营单位",
    "source": "企业预案_想咨询EPC总承办项目的应急预案备案问题，是建设单位还是总承办单位？.txt"
  },
  {
    "head": "生产经营单位",
    "relation": "应编制",
    "tail": "生产安全事故应急预案",
    "source": "企业预案_想咨询EPC总承办项目的应急预案备案问题，是建设单位还是总承办单位？.txt"
  },
  {
    "head": "国家安全生产应急救援中心",
    "relation": "回复",
    "tail": "咨询问题",
    "source": "企业预案_想咨询EPC总承办项目的应急预案备案问题，是建设单位还是总承办单位？.txt"
  }
]