[
  {
    "head": "政府负责人",
    "relation": "担任",
    "tail": "总指挥",
    "source": "其他_森林草原防灭火条例_林业_中国政府网.txt"
  },
  {
    "head": "政府负责人",
    "relation": "设置",
    "tail": "专业指挥",
    "source": "其他_森林草原防灭火条例_林业_中国政府网.txt"
  },
  {
    "head": "各类参与火灾扑救的救援力量",
    "relation": "接受统一指挥",
    "tail": "火场前线指挥部",
    "source": "其他_森林草原防灭火条例_林业_中国政府网.txt"
  },
  {
    "head": "火场前线指挥部",
    "relation": "核实",
    "tail": "火灾准确位置",
    "source": "其他_森林草原防灭火条例_林业_中国政府网.txt"
  },
  {
    "head": "火场前线指挥部",
    "relation": "核实",
    "tail": "火灾范围",
    "source": "其他_森林草原防灭火条例_林业_中国政府网.txt"
  },
  {
    "head": "火场前线指挥部",
    "relation": "核实",
    "tail": "风力",
    "source": "其他_森林草原防灭火条例_林业_中国政府网.txt"
  },
  {
    "head": "火场前线指挥部",
    "relation": "核实",
    "tail": "风向",
    "source": "其他_森林草原防灭火条例_林业_中国政府网.txt"
  },
  {
    "head": "火场前线指挥部",
    "relation": "核实",
    "tail": "火势",
    "source": "其他_森林草原防灭火条例_林业_中国政府网.txt"
  },
  {
    "head": "火场前线指挥部",
    "relation": "根据",
    "tail": "火灾现场天气条件",
    "source": "其他_森林草原防灭火条例_林业_中国政府网.txt"
  },
  {
    "head": "火场前线指挥部",
    "relation": "根据",
    "tail": "火灾现场地理条件",
    "source": "其他_森林草原防灭火条例_林业_中国政府网.txt"
  },
  {
    "head": "火场前线指挥部",
    "relation": "确定",
    "tail": "扑救方案",
    "source": "其他_森林草原防灭火条例_林业_中国政府网.txt"
  },
  {
    "head": "火场前线指挥部",
    "relation": "划分",
    "tail": "扑救地段",
    "source": "其他_森林草原防灭火条例_林业_中国政府网.txt"
  },
  {
    "head": "火场前线指挥部",
    "relation": "确定",
    "tail": "扑救责任人",
    "source": "其他_森林草原防灭火条例_林业_中国政府网.txt"
  },
  {
    "head": "火场前线指挥部",
    "relation": "防范处置",
    "tail": "险情",
    "source": "其他_森林草原防灭火条例_林业_中国政府网.txt"
  },
  {
    "head": "军事设施",
    "relation": "属于",
    "tail": "重要目标物",
    "source": "其他_森林草原防灭火条例_林业_中国政府网.txt"
  },
  {
    "head": "核设施",
    "relation": "属于",
    "tail": "重要目标物",
    "source": "其他_森林草原防灭火条例_林业_中国政府网.txt"
  },
  {
    "head": "危险化学品生产储存设施设备",
    "relation": "属于",
    "tail": "重要目标物",
    "source": "其他_森林草原防灭火条例_林业_中国政府网.txt"
  },
  {
    "head": "油气管道",
    "relation": "属于",
    "tail": "重要目标物",
    "source": "其他_森林草原防灭火条例_林业_中国政府网.txt"
  },
  {
    "head": "铁路线路",
    "relation": "属于",
    "tail": "重要目标物",
    "source": "其他_森林草原防灭火条例_林业_中国政府网.txt"
  },
  {
    "head": "重要目标物和重大危险源",
    "relation": "受到威胁",
    "tail": "火灾",
    "source": "其他_森林草原防灭火条例_林业_中国政府网.txt"
  },
  {
    "head": "专业人员",
    "relation": "指导",
    "tail": "消除威胁",
    "source": "其他_森林草原防灭火条例_林业_中国政府网.txt"
  },
  {
    "head": "专业人员",
    "relation": "指导",
    "tail": "科学施救",
    "source": "其他_森林草原防灭火条例_林业_中国政府网.txt"
  },
  {
    "head": "扑救森林草原火灾",
    "relation": "需要",
    "tail": "及时解救群众",
    "source": "其他_森林草原防灭火条例_林业_中国政府网.txt"
  },
  {
    "head": "扑救森林草原火灾",
    "relation": "需要",
    "tail": "疏散群众",
    "source": "其他_森林草原防灭火条例_林业_中国政府网.txt"
  },
  {
    "head": "扑救森林草原火灾",
    "relation": "需要",
    "tail": "撤离群众",
    "source": "其他_森林草原防灭火条例_林业_中国政府网.txt"
  },
  {
    "head": "扑救森林草原火灾",
    "relation": "需要",
    "tail": "做好火灾扑救人员管理",
    "source": "其他_森林草原防灭火条例_林业_中国政府网.txt"
  },
  {
    "head": "扑救森林草原火灾",
    "relation": "需要",
    "tail": "做好火灾扑救人员安全防护",
    "source": "其他_森林草原防灭火条例_林业_中国政府网.txt"
  },
  {
    "head": "扑救森林草原火灾",
    "relation": "目的",
    "tail": "保障扑救人员安全",
    "source": "其他_森林草原防灭火条例_林业_中国政府网.txt"
  },
  {
    "head": "扑救森林草原火灾",
    "relation": "目的",
    "tail": "避免人员伤亡",
    "source": "其他_森林草原防灭火条例_林业_中国政府网.txt"
  },
  {
    "head": "扑救森林草原火灾",
    "relation": "主力",
    "tail": "各类森林草原防灭火队伍",
    "source": "其他_森林草原防灭火条例_林业_中国政府网.txt"
  },
  {
    "head": "扑救森林草原火灾",
    "relation": "可组织",
    "tail": "干部群众协助",
    "source": "其他_森林草原防灭火条例_林业_中国政府网.txt"
  },
  {
    "head": "扑救森林草原火灾",
    "relation": "禁止安排",
    "tail": "未经培训人员直接灭火",
    "source": "其他_森林草原防灭火条例_林业_中国政府网.txt"
  },
  {
    "head": "扑救森林草原火灾",
    "relation": "禁止动员",
    "tail": "残疾人参加灭火",
    "source": "其他_森林草原防灭火条例_林业_中国政府网.txt"
  },
  {
    "head": "扑救森林草原火灾",
    "relation": "禁止动员",
    "tail": "孕妇参加灭火",
    "source": "其他_森林草原防灭火条例_林业_中国政府网.txt"
  },
  {
    "head": "扑救森林草原火灾",
    "relation": "禁止动员",
    "tail": "未成年人参加灭火",
    "source": "其他_森林草原防灭火条例_林业_中国政府网.txt"
  },
  {
    "head": "扑救森林草原火灾",
    "relation": "禁止动员",
    "tail": "其他不适宜人员参加灭火",
    "source": "其他_森林草原防灭火条例_林业_中国政府网.txt"
  },
  {
    "head": "有关地方人民政府",
    "relation": "组织",
    "tail": "地方森林草原消防队伍",
    "source": "其他_森林草原防灭火条例_林业_中国政府网.txt"
  },
  {
    "head": "有关地方人民政府",
    "relation": "组织",
    "tail": "国家综合性消防救援队伍",
    "source": "其他_森林草原防灭火条例_林业_中国政府网.txt"
  },
  {
    "head": "地方森林草原消防队伍",
    "relation": "参与",
    "tail": "扑救森林草原火灾",
    "source": "其他_森林草原防灭火条例_林业_中国政府网.txt"
  },
  {
    "head": "国家综合性消防救援队伍",
    "relation": "参与",
    "tail": "扑救森林草原火灾",
    "source": "其他_森林草原防灭火条例_林业_中国政府网.txt"
  },
  {
    "head": "国家综合性消防救援队伍",
    "relation": "调动按",
    "tail": "有关规定",
    "source": "其他_森林草原防灭火条例_林业_中国政府网.txt"
  },
  {
    "head": "国家综合性消防救援队伍",
    "relation": "执行任务",
    "tail": "森林草原火灾扑救任务",
    "source": "其他_森林草原防灭火条例_林业_中国政府网.txt"
  },
  {
    "head": "国家综合性消防救援队伍现场最高指挥员",
    "relation": "进入",
    "tail": "火场前线指挥部",
    "source": "其他_森林草原防灭火条例_林业_中国政府网.txt"
  },
  {
    "head": "国家综合性消防救援队伍现场最高指挥员",
    "relation": "负责",
    "tail": "专业指挥工作",
    "source": "其他_森林草原防灭火条例_林业_中国政府网.txt"
  },
  {
    "head": "国家综合性消防救援队伍现场最高指挥员",
    "relation": "参与",
    "tail": "决策",
    "source": "其他_森林草原防灭火条例_林业_中国政府网.txt"
  },
  {
    "head": "国家综合性消防救援队伍现场最高指挥员",
    "relation": "组织",
    "tail": "现场指挥",
    "source": "其他_森林草原防灭火条例_林业_中国政府网.txt"
  },
  {
    "head": "县级以上人民政府",
    "relation": "决定采取",
    "tail": "开设防火隔离带",
    "source": "其他_森林草原防灭火条例_林业_中国政府网.txt"
  },
  {
    "head": "县级以上人民政府",
    "relation": "决定采取",
    "tail": "清除障碍物",
    "source": "其他_森林草原防灭火条例_林业_中国政府网.txt"
  },
  {
    "head": "县级以上人民政府",
    "relation": "决定采取",
    "tail": "应急取水",
    "source": "其他_森林草原防灭火条例_林业_中国政府网.txt"
  },
  {
    "head": "县级以上人民政府",
    "relation": "决定采取",
    "tail": "局部交通管制",
    "source": "其他_森林草原防灭火条例_林业_中国政府网.txt"
  },
  {
    "head": "国家",
    "relation": "实行",
    "tail": "森林草原火灾信息统一发布制度",
    "source": "其他_森林草原防灭火条例_林业_中国政府网.txt"
  },
  {
    "head": "森林草原火灾信息",
    "relation": "由",
    "tail": "县级以上人民政府应急管理部门发布",
    "source": "其他_森林草原防灭火条例_林业_中国政府网.txt"
  },
  {
    "head": "特别重大森林草原火灾信息",
    "relation": "由",
    "tail": "省级人民政府发布",
    "source": "其他_森林草原防灭火条例_林业_中国政府网.txt"
  },
  {
    "head": "重大森林草原火灾信息",
    "relation": "由",
    "tail": "省级人民政府发布",
    "source": "其他_森林草原防灭火条例_林业_中国政府网.txt"
  },
  {
    "head": "特别重大森林草原火灾信息",
    "relation": "可由",
    "tail": "国家森林草原防灭火指挥部发布",
    "source": "其他_森林草原防灭火条例_林业_中国政府网.txt"
  },
  {
    "head": "重大森林草原火灾信息",
    "relation": "可由",
    "tail": "国务院应急管理部门发布",
    "source": "其他_森林草原防灭火条例_林业_中国政府网.txt"
  },
  {
    "head": "县级以上人民政府应急管理部门",
    "relation": "发布",
    "tail": "森林草原火灾和应对工作情况",
    "source": "其他_森林草原防灭火条例_林业_中国政府网.txt"
  },
  {
    "head": "任何单位和个人",
    "relation": "禁止",
    "tail": "编造虚假信息",
    "source": "其他_森林草原防灭火条例_林业_中国政府网.txt"
  },
  {
    "head": "任何单位和个人",
    "relation": "禁止",
    "tail": "故意传播虚假信息",
    "source": "其他_森林草原防灭火条例_林业_中国政府网.txt"
  },
  {
    "head": "扑救队伍",
    "relation": "检查",
    "tail": "火灾现场",
    "source": "其他_森林草原防灭火条例_林业_中国政府网.txt"
  },
  {
    "head": "扑救队伍",
    "relation": "清理",
    "tail": "余火",
    "source": "其他_森林草原防灭火条例_林业_中国政府网.txt"
  },
  {
    "head": "当地人民政府",
    "relation": "组织",
    "tail": "人员看守火场",
    "source": "其他_森林草原防灭火条例_林业_中国政府网.txt"
  },
  {
    "head": "当地人民政府",
    "relation": "检查验收",
    "tail": "火场",
    "source": "其他_森林草原防灭火条例_林业_中国政府网.txt"
  },
  {
    "head": "看守人员",
    "relation": "撤出",
    "tail": "经检查验收合格后",
    "source": "其他_森林草原防灭火条例_林业_中国政府网.txt"
  },
  {
    "head": "县级以上人民政府",
    "relation": "建立",
    "tail": "工作机制",
    "source": "其他_森林草原防灭火条例_林业_中国政府网.txt"
  },
  {
    "head": "县级以上人民政府",
    "relation": "征用",
    "tail": "场地",
    "source": "其他_森林草原防灭火条例_林业_中国政府网.txt"
  },
  {
    "head": "县级以上人民政府",
    "relation": "征用",
    "tail": "物资",
    "source": "其他_森林草原防灭火条例_林业_中国政府网.txt"
  },
  {
    "head": "县级以上人民政府",
    "relation": "征用",
    "tail": "设备",
    "source": "其他_森林草原防灭火条例_林业_中国政府网.txt"
  },
  {
    "head": "县级以上人民政府",
    "relation": "征用",
    "tail": "交通运输工具",
    "source": "其他_森林草原防灭火条例_林业_中国政府网.txt"
  },
  {
    "head": "县级以上人民政府",
    "relation": "返还",
    "tail": "征用物品",
    "source": "其他_森林草原防灭火条例_林业_中国政府网.txt"
  },
  {
    "head": "县级以上人民政府",
    "relation": "给予",
    "tail": "补偿",
    "source": "其他_森林草原防灭火条例_林业_中国政府网.txt"
  },
  {
    "head": "森林草原火灾",
    "relation": "分为",
    "tail": "一般等级",
    "source": "其他_森林草原防灭火条例_林业_中国政府网.txt"
  },
  {
    "head": "森林草原火灾",
    "relation": "分为",
    "tail": "较大等级",
    "source": "其他_森林草原防灭火条例_林业_中国政府网.txt"
  },
  {
    "head": "森林草原火灾",
    "relation": "分为",
    "tail": "重大等级",
    "source": "其他_森林草原防灭火条例_林业_中国政府网.txt"
  },
  {
    "head": "森林草原火灾",
    "relation": "分为",
    "tail": "特别重大等级",
    "source": "其他_森林草原防灭火条例_林业_中国政府网.txt"
  },
  {
    "head": "一般森林火灾",
    "relation": "受害森林面积",
    "tail": "0.067公顷以上10公顷以下",
    "source": "其他_森林草原防灭火条例_林业_中国政府网.txt"
  },
  {
    "head": "一般森林火灾",
    "relation": "死亡人数",
    "tail": "1人以上3人以下",
    "source": "其他_森林草原防灭火条例_林业_中国政府网.txt"
  },
  {
    "head": "一般森林火灾",
    "relation": "重伤人数",
    "tail": "1人以上10人以下",
    "source": "其他_森林草原防灭火条例_林业_中国政府网.txt"
  },
  {
    "head": "较大森林火灾",
    "relation": "受害森林面积",
    "tail": "10公顷以上100公顷以下",
    "source": "其他_森林草原防灭火条例_林业_中国政府网.txt"
  },
  {
    "head": "较大森林火灾",
    "relation": "死亡人数",
    "tail": "3人以上10人以下",
    "source": "其他_森林草原防灭火条例_林业_中国政府网.txt"
  },
  {
    "head": "较大森林火灾",
    "relation": "重伤人数",
    "tail": "10人以上50人以下",
    "source": "其他_森林草原防灭火条例_林业_中国政府网.txt"
  },
  {
    "head": "重大森林火灾",
    "relation": "受害森林面积",
    "tail": "100公顷以上1000公顷以下",
    "source": "其他_森林草原防灭火条例_林业_中国政府网.txt"
  },
  {
    "head": "重大森林火灾",
    "relation": "死亡人数",
    "tail": "10人以上30人以下",
    "source": "其他_森林草原防灭火条例_林业_中国政府网.txt"
  },
  {
    "head": "重大森林火灾",
    "relation": "重伤人数",
    "tail": "50人以上100人以下",
    "source": "其他_森林草原防灭火条例_林业_中国政府网.txt"
  },
  {
    "head": "特别重大森林火灾",
    "relation": "受害森林面积",
    "tail": "1000公顷以上",
    "source": "其他_森林草原防灭火条例_林业_中国政府网.txt"
  },
  {
    "head": "特别重大森林火灾",
    "relation": "死亡人数",
    "tail": "30人以上",
    "source": "其他_森林草原防灭火条例_林业_中国政府网.txt"
  },
  {
    "head": "特别重大森林火灾",
    "relation": "重伤人数",
    "tail": "100人以上",
    "source": "其他_森林草原防灭火条例_林业_中国政府网.txt"
  },
  {
    "head": "一般草原火灾",
    "relation": "受害草原面积",
    "tail": "10公顷以上1000公顷以下",
    "source": "其他_森林草原防灭火条例_林业_中国政府网.txt"
  },
  {
    "head": "一般草原火灾",
    "relation": "死亡人数",
    "tail": "1人以上3人以下",
    "source": "其他_森林草原防灭火条例_林业_中国政府网.txt"
  },
  {
    "head": "一般草原火灾",
    "relation": "重伤人数",
    "tail": "1人以上10人以下",
    "source": "其他_森林草原防灭火条例_林业_中国政府网.txt"
  },
  {
    "head": "较大草原火灾",
    "relation": "受害草原面积",
    "tail": "1000公顷以上5000公顷以下",
    "source": "其他_森林草原防灭火条例_林业_中国政府网.txt"
  },
  {
    "head": "较大草原火灾",
    "relation": "死亡人数",
    "tail": "3人以上10人以下",
    "source": "其他_森林草原防灭火条例_林业_中国政府网.txt"
  },
  {
    "head": "较大草原火灾",
    "relation": "重伤人数",
    "tail": "10人以上50人以下",
    "source": "其他_森林草原防灭火条例_林业_中国政府网.txt"
  },
  {
    "head": "重大草原火灾",
    "relation": "受害草原面积",
    "tail": "5000公顷以上8000公顷以下",
    "source": "其他_森林草原防灭火条例_林业_中国政府网.txt"
  },
  {
    "head": "重大草原火灾",
    "relation": "死亡人数",
    "tail": "10人以上30人以下",
    "source": "其他_森林草原防灭火条例_林业_中国政府网.txt"
  },
  {
    "head": "重大草原火灾",
    "relation": "重伤人数",
    "tail": "50人以上100人以下",
    "source": "其他_森林草原防灭火条例_林业_中国政府网.txt"
  },
  {
    "head": "特别重大草原火灾",
    "relation": "受害草原面积",
    "tail": "8000公顷以上",
    "source": "其他_森林草原防灭火条例_林业_中国政府网.txt"
  },
  {
    "head": "特别重大草原火灾",
    "relation": "死亡人数",
    "tail": "30人以上",
    "source": "其他_森林草原防灭火条例_林业_中国政府网.txt"
  },
  {
    "head": "特别重大草原火灾",
    "relation": "重伤人数",
    "tail": "100人以上",
    "source": "其他_森林草原防灭火条例_林业_中国政府网.txt"
  },
  {
    "head": "县级以上人民政府",
    "relation": "组织",
    "tail": "有关部门",
    "source": "其他_森林草原防灭火条例_林业_中国政府网.txt"
  },
  {
    "head": "有关部门",
    "relation": "调查评估",
    "tail": "森林草原火灾发生原因",
    "source": "其他_森林草原防灭火条例_林业_中国政府网.txt"
  },
  {
    "head": "有关部门",
    "relation": "调查评估",
    "tail": "受害面积和蓄积",
    "source": "其他_森林草原防灭火条例_林业_中国政府网.txt"
  },
  {
    "head": "有关部门",
    "relation": "调查评估",
    "tail": "人员伤亡",
    "source": "其他_森林草原防灭火条例_林业_中国政府网.txt"
  },
  {
    "head": "有关部门",
    "relation": "调查评估",
    "tail": "其他经济损失",
    "source": "其他_森林草原防灭火条例_林业_中国政府网.txt"
  },
  {
    "head": "有关部门",
    "relation": "调查评估",
    "tail": "生态环境影响",
    "source": "其他_森林草原防灭火条例_林业_中国政府网.txt"
  },
  {
    "head": "有关部门",
    "relation": "调查评估",
    "tail": "应急救援处置情况",
    "source": "其他_森林草原防灭火条例_林业_中国政府网.txt"
  },
  {
    "head": "有关部门",
    "relation": "形成",
    "tail": "调查评估报告",
    "source": "其他_森林草原防灭火条例_林业_中国政府网.txt"
  },
  {
    "head": "当地人民政府",
    "relation": "根据",
    "tail": "调查评估报告",
    "source": "其他_森林草原防灭火条例_林业_中国政府网.txt"
  },
  {
    "head": "当地人民政府",
    "relation": "确定",
    "tail": "火灾责任单位",
    "source": "其他_森林草原防灭火条例_林业_中国政府网.txt"
  },
  {
    "head": "当地人民政府",
    "relation": "确定",
    "tail": "火灾责任人",
    "source": "其他_森林草原防灭火条例_林业_中国政府网.txt"
  },
  {
    "head": "当地人民政府",
    "relation": "依法处理",
    "tail": "责任单位、责任人",
    "source": "其他_森林草原防灭火条例_林业_中国政府网.txt"
  },
  {
    "head": "森林草原火灾调查评估工作",
    "relation": "执行",
    "tail": "国家有关规定",
    "source": "其他_森林草原防灭火条例_林业_中国政府网.txt"
  },
  {
    "head": "国务院林业草原主管部门",
    "relation": "会同",
    "tail": "有关部门",
    "source": "其他_森林草原防灭火条例_林业_中国政府网.txt"
  },
  {
    "head": "国务院林业草原主管部门",
    "relation": "制定",
    "tail": "森林草原火灾损失评估标准",
    "source": "其他_森林草原防灭火条例_林业_中国政府网.txt"
  },
  {
    "head": "森林草原火灾等级",
    "relation": "根据",
    "tail": "调查评估报告",
    "source": "其他_森林草原防灭火条例_林业_中国政府网.txt"
  },
  {
    "head": "灌木林地起火未造成林木受害",
    "relation": "不统计为",
    "tail": "火灾",
    "source": "其他_森林草原防灭火条例_林业_中国政府网.txt"
  },
  {
    "head": "疏林地起火未造成林木受害",
    "relation": "不统计为",
    "tail": "火灾",
    "source": "其他_森林草原防灭火条例_林业_中国政府网.txt"
  },
  {
    "head": "未成林造林地起火未造成林木受害",
    "relation": "不统计为",
    "tail": "火灾",
    "source": "其他_森林草原防灭火条例_林业_中国政府网.txt"
  },
  {
    "head": "苗圃地起火未造成林木受害",
    "relation": "不统计为",
    "tail": "火灾",
    "source": "其他_森林草原防灭火条例_林业_中国政府网.txt"
  },
  {
    "head": "受害森林面积不足0.067公顷",
    "relation": "不统计为",
    "tail": "火灾",
    "source": "其他_森林草原防灭火条例_林业_中国政府网.txt"
  },
  {
    "head": "受害草原面积不足10公顷",
    "relation": "不统计为",
    "tail": "火灾",
    "source": "其他_森林草原防灭火条例_林业_中国政府网.txt"
  },
  {
    "head": "未造成人员死亡重伤",
    "relation": "不统计为",
    "tail": "火灾",
    "source": "其他_森林草原防灭火条例_林业_中国政府网.txt"
  },
  {
    "head": "县级以上地方人民政府森林草原防灭火指挥机构",
    "relation": "统计",
    "tail": "森林草原火灾情况",
    "source": "其他_森林草原防灭火条例_林业_中国政府网.txt"
  },
  {
    "head": "县级以上地方人民政府森林草原防灭火指挥机构",
    "relation": "上报",
    "tail": "上级人民政府森林草原防灭火指挥机构",
    "source": "其他_森林草原防灭火条例_林业_中国政府网.txt"
  },
  {
    "head": "县级以上地方人民政府森林草原防灭火指挥机构",
    "relation": "上报",
    "tail": "本级人民政府统计机构",
    "source": "其他_森林草原防灭火条例_林业_中国政府网.txt"
  },
  {
    "head": "县级以上地方人民政府森林草原防灭火指挥机构",
    "relation": "通报",
    "tail": "本级人民政府有关部门",
    "source": "其他_森林草原防灭火条例_林业_中国政府网.txt"
  },
  {
    "head": "国务院应急管理部门",
    "relation": "会同",
    "tail": "有关部门",
    "source": "其他_森林草原防灭火条例_林业_中国政府网.txt"
  },
  {
    "head": "国务院应急管理部门",
    "relation": "制定",
    "tail": "森林草原火灾统计调查项目",
    "source": "其他_森林草原防灭火条例_林业_中国政府网.txt"
  },
  {
    "head": "国务院应急管理部门",
    "relation": "制定",
    "tail": "森林草原火灾统计调查制度",
    "source": "其他_森林草原防灭火条例_林业_中国政府网.txt"
  },
  {
    "head": "因扑救森林草原火灾负伤人员",
    "relation": "给予",
    "tail": "医疗救治",
    "source": "其他_森林草原防灭火条例_林业_中国政府网.txt"
  },
  {
    "head": "因扑救森林草原火灾负伤人员",
    "relation": "给予",
    "tail": "抚恤优待",
    "source": "其他_森林草原防灭火条例_林业_中国政府网.txt"
  },
  {
    "head": "因扑救森林草原火灾致残人员",
    "relation": "给予",
    "tail": "医疗救治",
    "source": "其他_森林草原防灭火条例_林业_中国政府网.txt"
  },
  {
    "head": "因扑救森林草原火灾致残人员",
    "relation": "给予",
    "tail": "抚恤优待",
    "source": "其他_森林草原防灭火条例_林业_中国政府网.txt"
  },
  {
    "head": "因扑救森林草原火灾死亡人员",
    "relation": "给予",
    "tail": "抚恤优待",
    "source": "其他_森林草原防灭火条例_林业_中国政府网.txt"
  },
  {
    "head": "符合烈士评定条件",
    "relation": "评定为",
    "tail": "烈士",
    "source": "其他_森林草原防灭火条例_林业_中国政府网.txt"
  },
  {
    "head": "参加森林草原火灾扑救的人员",
    "relation": "享受",
    "tail": "人身保险待遇",
    "source": "其他_森林草原防灭火条例_林业_中国政府网.txt"
  },
  {
    "head": "用人单位",
    "relation": "保证",
    "tail": "职工工资待遇不变",
    "source": "其他_森林草原防灭火条例_林业_中国政府网.txt"
  },
  {
    "head": "用人单位",
    "relation": "保证",
    "tail": "职工福利不变",
    "source": "其他_森林草原防灭火条例_林业_中国政府网.txt"
  },
  {
    "head": "参加扑救人员",
    "relation": "补贴补助由",
    "tail": "火灾责任单位支付",
    "source": "其他_森林草原防灭火条例_林业_中国政府网.txt"
  },
  {
    "head": "火灾责任单位",
    "relation": "支付",
    "tail": "扑救费用",
    "source": "其他_森林草原防灭火条例_林业_中国政府网.txt"
  },
  {
    "head": "火灾责任人",
    "relation": "支付",
    "tail": "扑救费用",
    "source": "其他_森林草原防灭火条例_林业_中国政府网.txt"
  },
  {
    "head": "起火原因不清",
    "relation": "由",
    "tail": "起火单位支付扑救费用",
    "source": "其他_森林草原防灭火条例_林业_中国政府网.txt"
  },
  {
    "head": "当地人民政府",
    "relation": "先行垫付",
    "tail": "扑救费用",
    "source": "其他_森林草原防灭火条例_林业_中国政府网.txt"
  },
  {
    "head": "森林经营单位和个人",
    "relation": "采取",
    "tail": "更新造林措施",
    "source": "其他_森林草原防灭火条例_林业_中国政府网.txt"
  },
  {
    "head": "林木经营单位和个人",
    "relation": "采取",
    "tail": "更新造林措施",
    "source": "其他_森林草原防灭火条例_林业_中国政府网.txt"
  },
  {
    "head": "林地经营单位和个人",
    "relation": "采取",
    "tail": "更新造林措施",
    "source": "其他_森林草原防灭火条例_林业_中国政府网.txt"
  },
  {
    "head": "草原经营单位和个人",
    "relation": "采取",
    "tail": "更新造林措施",
    "source": "其他_森林草原防灭火条例_林业_中国政府网.txt"
  },
  {
    "head": "更新造林措施",
    "relation": "恢复",
    "tail": "火烧迹地森林植被",
    "source": "其他_森林草原防灭火条例_林业_中国政府网.txt"
  },
  {
    "head": "更新造林措施",
    "relation": "恢复",
    "tail": "林业生产条件",
    "source": "其他_森林草原防灭火条例_林业_中国政府网.txt"
  },
  {
    "head": "更新造林措施",
    "relation": "恢复",
    "tail": "牧业生产条件",
    "source": "其他_森林草原防灭火条例_林业_中国政府网.txt"
  },
  {
    "head": "当地人民政府",
    "relation": "提供",
    "tail": "必要支持",
    "source": "其他_森林草原防灭火条例_林业_中国政府网.txt"
  },
  {
    "head": "地方各级人民政府等",
    "relation": "未编制",
    "tail": "森林草原火灾应急预案",
    "source": "其他_森林草原防灭火条例_林业_中国政府网.txt"
  },
  {
    "head": "地方各级人民政府等",
    "relation": "未组织开展",
    "tail": "森林草原火灾应急预案演练",
    "source": "其他_森林草原防灭火条例_林业_中国政府网.txt"
  },
  {
    "head": "发现火灾隐患",
    "relation": "未下达",
    "tail": "整改通知书",
    "source": "其他_森林草原防灭火条例_林业_中国政府网.txt"
  },
  {
    "head": "批准行为",
    "relation": "批准",
    "tail": "不符合要求的野外用火",
    "source": "其他_森林草原防灭火条例_林业_中国政府网.txt"
  },
  {
    "head": "批准行为",
    "relation": "批准",
    "tail": "不符合要求的非军事实弹演习",
    "source": "其他_森林草原防灭火条例_林业_中国政府网.txt"
  },
  {
    "head": "瞒报行为",
    "relation": "瞒报",
    "tail": "森林草原火情",
    "source": "其他_森林草原防灭火条例_林业_中国政府网.txt"
  },
  {
    "head": "谎报行为",
    "relation": "谎报",
    "tail": "森林草原火情",
    "source": "其他_森林草原防灭火条例_林业_中国政府网.txt"
  },
  {
    "head": "故意拖延报告行为",
    "relation": "故意拖延报告",
    "tail": "森林草原火情",
    "source": "其他_森林草原防灭火条例_林业_中国政府网.txt"
  },
  {
    "head": "预警信息发布后",
    "tail": "预警相应措施",
    "source": "其他_森林草原防灭火条例_林业_中国政府网.txt"
  },
  {
    "head": "处置措施",
    "tail": "处置措施",
    "source": "其他_森林草原防灭火条例_林业_中国政府网.txt"
  },
  {
    "head": "弄虚作假行为",
    "tail": "弄虚作假",
    "source": "其他_森林草原防灭火条例_林业_中国政府网.txt"
  },
  {
    "head": "违反本条例行为",
    "relation": "上级行政机关责令改正",
    "tail": "上级行政机关",
    "source": "其他_森林草原防灭火条例_林业_中国政府网.txt"
  },
  {
    "head": "情节严重的",
    "relation": "对领导人员和直接责任人员",
    "tail": "给予处分",
    "source": "其他_森林草原防灭火条例_林业_中国政府网.txt"
  },
  {
    "head": "森林经营单位未履行防灭火责任",
    "relation": "责令改正",
    "tail": "责令改正",
    "source": "其他_森林草原防灭火条例_林业_中国政府网.txt"
  },
  {
    "head": "森林经营单位未履行防灭火责任",
    "relation": "罚款",
    "tail": "2万元以上10万元以下",
    "source": "其他_森林草原防灭火条例_林业_中国政府网.txt"
  },
  {
    "head": "个人未履行防灭火责任",
    "relation": "罚款",
    "tail": "1000元以上1万元以下",
    "source": "其他_森林草原防灭火条例_林业_中国政府网.txt"
  },
  {
    "head": "拒不改正",
    "relation": "对单位罚款",
    "tail": "5万元以上20万元以下",
    "source": "其他_森林草原防灭火条例_林业_中国政府网.txt"
  },
  {
    "head": "拒不改正",
    "relation": "对个人罚款",
    "tail": "2000元以上2万元以下",
    "source": "其他_森林草原防灭火条例_林业_中国政府网.txt"
  },
  {
    "head": "防火区内单位拒绝接受检查",
    "relation": "罚款",
    "tail": "1万元以上2万元以下",
    "source": "其他_森林草原防灭火条例_林业_中国政府网.txt"
  },
  {
    "head": "防火区内个人拒绝接受检查",
    "relation": "罚款",
    "tail": "300元以上3000元以下",
    "source": "其他_森林草原防灭火条例_林业_中国政府网.txt"
  },
  {
    "head": "单位逾期不消除隐患",
    "relation": "罚款",
    "tail": "1万元以上2万元以下",
    "source": "其他_森林草原防灭火条例_林业_中国政府网.txt"
  },
  {
    "head": "个人逾期不消除隐患",
    "relation": "罚款",
    "tail": "300元以上3000元以下",
    "source": "其他_森林草原防灭火条例_林业_中国政府网.txt"
  },
  {
    "head": "单位未经批准野外用火",
    "relation": "罚款",
    "tail": "2万元以上10万元以下",
    "source": "其他_森林草原防灭火条例_林业_中国政府网.txt"
  },
  {
    "head": "个人未经批准野外用火",
    "relation": "罚款",
    "tail": "300元以上5000元以下",
    "source": "其他_森林草原防灭火条例_林业_中国政府网.txt"
  },
  {
    "head": "单位未经批准进行非军事实弹演习",
    "relation": "罚款",
    "tail": "10万元以上20万元以下",
    "source": "其他_森林草原防灭火条例_林业_中国政府网.txt"
  },
  {
    "head": "单位未设置防火警示标志",
    "relation": "罚款",
    "tail": "5000元以上2万元以下",
    "source": "其他_森林草原防灭火条例_林业_中国政府网.txt"
  },
  {
    "head": "个人未设置防火警示标志",
    "relation": "罚款",
    "tail": "300元以上3000元以下",
    "source": "其他_森林草原防灭火条例_林业_中国政府网.txt"
  },
  {
    "head": "单位未安装防火装置",
    "relation": "罚款",
    "tail": "5000元以上2万元以下",
    "source": "其他_森林草原防灭火条例_林业_中国政府网.txt"
  },
  {
    "head": "个人未安装防火装置",
    "relation": "罚款",
    "tail": "300元以上3000元以下",
    "source": "其他_森林草原防灭火条例_林业_中国政府网.txt"
  },
  {
    "head": "机械设备未采取防火措施",
    "relation": "罚款",
    "tail": "5000元以上2万元以下",
    "source": "其他_森林草原防灭火条例_林业_中国政府网.txt"
  },
  {
    "head": "作业人员不遵守防火操作规程",
    "relation": "罚款",
    "tail": "300元以上3000元以下",
    "source": "其他_森林草原防灭火条例_林业_中国政府网.txt"
  },
  {
    "head": "车辆拒绝防火登记",
    "relation": "罚款",
    "tail": "300元以上3000元以下",
    "source": "其他_森林草原防灭火条例_林业_中国政府网.txt"
  },
  {
    "head": "人员拒绝防火登记",
    "relation": "罚款",
    "tail": "300元以上3000元以下",
    "source": "其他_森林草原防灭火条例_林业_中国政府网.txt"
  },
  {
    "head": "未经批准进入高火险区",
    "relation": "罚款",
    "tail": "300元以上3000元以下",
    "source": "其他_森林草原防灭火条例_林业_中国政府网.txt"
  },
  {
    "head": "未按批准活动",
    "relation": "罚款",
    "tail": "300元以上3000元以下",
    "source": "其他_森林草原防灭火条例_林业_中国政府网.txt"
  },
  {
    "head": "在防火区内丢弃火种",
    "relation": "罚款",
    "tail": "300元以上3000元以下",
    "source": "其他_森林草原防灭火条例_林业_中国政府网.txt"
  },
  {
    "head": "破坏防灭火设施设备",
    "relation": "罚款",
    "tail": "5000元以上2万元以下",
    "source": "其他_森林草原防灭火条例_林业_中国政府网.txt"
  },
  {
    "head": "开办农牧场未配套防火设施",
    "relation": "罚款",
    "tail": "5000元以上2万元以下",
    "source": "其他_森林草原防灭火条例_林业_中国政府网.txt"
  },
  {
    "head": "设立旅游区未配套防火设施",
    "relation": "罚款",
    "tail": "5000元以上2万元以下",
    "source": "其他_森林草原防灭火条例_林业_中国政府网.txt"
  },
  {
    "head": "新建开发区未配套防火设施",
    "relation": "罚款",
    "tail": "5000元以上2万元以下",
    "source": "其他_森林草原防灭火条例_林业_中国政府网.txt"
  },
  {
    "head": "成片造林未配套防火设施",
    "relation": "罚款",
    "tail": "5000元以上2万元以下",
    "source": "其他_森林草原防灭火条例_林业_中国政府网.txt"
  },
  {
    "head": "成片种草未配套防火设施",
    "relation": "罚款",
    "tail": "5000元以上2万元以下",
    "source": "其他_森林草原防灭火条例_林业_中国政府网.txt"
  },
  {
    "head": "新建设施未验收合格",
    "relation": "罚款",
    "tail": "5000元以上2万元以下",
    "source": "其他_森林草原防灭火条例_林业_中国政府网.txt"
  },
  {
    "head": "编造虚假信息",
    "relation": "予以处罚",
    "tail": "依法",
    "source": "其他_森林草原防灭火条例_林业_中国政府网.txt"
  },
  {
    "head": "传播虚假信息",
    "relation": "予以处罚",
    "tail": "依法",
    "source": "其他_森林草原防灭火条例_林业_中国政府网.txt"
  },
  {
    "head": "责任单位",
    "relation": "补种",
    "tail": "树木",
    "source": "其他_森林草原防灭火条例_林业_中国政府网.txt"
  },
  {
    "head": "责任单位",
    "relation": "恢复",
    "tail": "植被",
    "source": "其他_森林草原防灭火条例_林业_中国政府网.txt"
  },
  {
    "head": "责任人",
    "relation": "补种",
    "tail": "树木",
    "source": "其他_森林草原防灭火条例_林业_中国政府网.txt"
  },
  {
    "head": "责任人",
    "relation": "恢复",
    "tail": "植被",
    "source": "其他_森林草原防灭火条例_林业_中国政府网.txt"
  },
  {
    "head": "违反治安管理行为",
    "relation": "给予",
    "tail": "治安管理处罚",
    "source": "其他_森林草原防灭火条例_林业_中国政府网.txt"
  },
  {
    "head": "犯罪行为",
    "relation": "追究",
    "tail": "刑事责任",
    "source": "其他_森林草原防灭火条例_林业_中国政府网.txt"
  },
  {
    "head": "森林草原消防车辆",
    "relation": "享受",
    "tail": "应急救援车辆政策",
    "source": "其他_森林草原防灭火条例_林业_中国政府网.txt"
  },
  {
    "head": "森林草原消防车辆",
    "relation": "编制核定按",
    "tail": "党政机关特种专业技术用车规定",
    "source": "其他_森林草原防灭火条例_林业_中国政府网.txt"
  },
  {
    "head": "森林草原消防车辆",
    "relation": "配备按",
    "tail": "党政机关特种专业技术用车规定",
    "source": "其他_森林草原防灭火条例_林业_中国政府网.txt"
  },
  {
    "head": "森林草原消防车辆",
    "relation": "喷涂",
    "tail": "标志图案",
    "source": "其他_森林草原防灭火条例_林业_中国政府网.txt"
  },
  {
    "head": "森林草原消防车辆",
    "relation": "安装",
    "tail": "报警器",
    "source": "其他_森林草原防灭火条例_林业_中国政府网.txt"
  },
  {
    "head": "森林草原消防车辆",
    "relation": "安装",
    "tail": "标志灯具",
    "source": "其他_森林草原防灭火条例_林业_中国政府网.txt"
  },
  {
    "head": "边境地区森林草原火灾",
    "relation": "扑救工作按",
    "tail": "国际协定或合作机制",
    "source": "其他_森林草原防灭火条例_林业_中国政府网.txt"
  },
  {
    "head": "无协定机制",
    "relation": "协商办理",
    "tail": "扑救工作",
    "source": "其他_森林草原防灭火条例_林业_中国政府网.txt"
  },
  {
    "head": "林牧区军事设施防灭火工作",
    "relation": "适用",
    "tail": "军事法规",
    "source": "其他_森林草原防灭火条例_林业_中国政府网.txt"
  },
  {
    "head": "军事区域防灭火基础设施",
    "relation": "建设按",
    "tail": "军事法规",
    "source": "其他_森林草原防灭火条例_林业_中国政府网.txt"
  },
  {
    "head": "中国人民解放军",
    "relation": "执行",
    "tail": "森林草原火灾扑救任务",
    "source": "其他_森林草原防灭火条例_林业_中国政府网.txt"
  },
  {
    "head": "中国人民武装警察部队",
    "relation": "执行",
    "tail": "森林草原火灾扑救任务",
    "source": "其他_森林草原防灭火条例_林业_中国政府网.txt"
  },
  {
    "head": "民兵组织",
    "relation": "执行",
    "tail": "森林草原火灾扑救任务",
    "source": "其他_森林草原防灭火条例_林业_中国政府网.txt"
  },
  {
    "head": "本条例",
    "relation": "施行日期",
    "tail": "2026年1月1日",
    "source": "其他_森林草原防灭火条例_林业_中国政府网.txt"
  },
  {
    "head": "《森林防火条例》",
    "relation": "废止",
    "tail": "自2026年1月1日",
    "source": "其他_森林草原防灭火条例_林业_中国政府网.txt"
  },
  {
    "head": "《草原防火条例》",
    "relation": "废止",
    "tail": "自2026年1月1日",
    "source": "其他_森林草原防灭火条例_林业_中国政府网.txt"
  }
]